aiocfd1/__init__.py
aiocfd1/core.py
aiocfd1-1.0.0.dist-info/licenses/LICENSE
aiocfd1-1.0.0.dist-info/METADATA
aiocfd1-1.0.0.dist-info/WHEEL
aiocfd1-1.0.0.dist-info/top_level.txt
aiocfd1-1.0.0.dist-info/RECORD
